libhoney/__init__.py
libhoney/builder.py
libhoney/client.py
libhoney/errors.py
libhoney/event.py
libhoney/fields.py
libhoney/internal.py
libhoney/state.py
libhoney/test_client.py
libhoney/test_libhoney.py
libhoney/test_tornado.py
libhoney/test_transmission.py
libhoney/transmission.py
libhoney/version.py
libhoney-2.4.0.dist-info/LICENSE
libhoney-2.4.0.dist-info/METADATA
libhoney-2.4.0.dist-info/WHEEL
libhoney-2.4.0.dist-info/RECORD
