Metadata-Version: 2.1
Name: libhoney
Version: 2.4.0
Summary: Python library for sending data to Honeycomb
Home-page: https://github.com/honeycombio/libhoney-py
License: Apache-2.0
Author: Honeycomb.io
Author-email: feedback@honeycomb.io
Requires-Python: >=3.7,<4
Classifier: License :: OSI Approved :: Apache Software License
Classifier: Programming Language :: Python :: 3
Classifier: Programming Language :: Python :: 3.7
Classifier: Programming Language :: Python :: 3.8
Classifier: Programming Language :: Python :: 3.9
Classifier: Programming Language :: Python :: 3.10
Classifier: Programming Language :: Python :: 3.11
Requires-Dist: requests (>=2.24.0,<3.0.0)
Requires-Dist: statsd (>=3.3,<5.0)
Requires-Dist: urllib3 (>=1.26,<3.0)
Project-URL: Repository, https://github.com/honeycombio/libhoney-py
